kestrel_analytics_python/__init__.py
kestrel_analytics_python/config.py
kestrel_analytics_python/interface.py
kestrel_analytics_python-1.8.0.dist-info/METADATA
kestrel_analytics_python-1.8.0.dist-info/WHEEL
kestrel_analytics_python-1.8.0.dist-info/top_level.txt
kestrel_analytics_python-1.8.0.dist-info/RECORD
