Metadata-Version: 2.1
Name: kestrel_analytics_python
Version: 1.8.0
Summary: Kestrel Python Analytics Interface
Maintainer-email: Xiaokui Shu <xiaokui.shu@ibm.com>, Paul Coccoli <pcoccoli@us.ibm.com>
License: Apache 2.0 License
Project-URL: Homepage, https://github.com/opencybersecurityalliance/kestrel-lang
Project-URL: Documentation, https://kestrel.readthedocs.io/
Project-URL: Repository, https://github.com/opencybersecurityalliance/kestrel-lang.git
Keywords: kestrel,analytics,interface,python
Classifier: Topic :: Security
Classifier: Operating System :: OS Independent
Classifier: Development Status :: 4 - Beta
Classifier: Programming Language :: Python :: 3
Requires-Python: >=3.8
Requires-Dist: kestrel_core>=1.8.0
Provides-Extra: test
Requires-Dist: pytest; extra == "test"
Requires-Dist: kestrel_datasource_stixbundle; extra == "test"
